movphot/__init__.py
movphot/common.py
movphot/movphot.py
movphot/photfunc.py
movphot/psdb.py
movphot/visualization.py
movphot/scripts/phot_color.py
movphot/scripts/plot_colorterm.py
movphot-0.0.1.dist-info/LICENCE
movphot-0.0.1.dist-info/METADATA
movphot-0.0.1.dist-info/WHEEL
movphot-0.0.1.dist-info/entry_points.txt
movphot-0.0.1.dist-info/top_level.txt
movphot-0.0.1.dist-info/RECORD
