Metadata-Version: 2.1
Name: movphot
Version: 0.0.1
Summary: moving object photometry
Home-page: https://bitbucket.org/jin_beniyama/movphot/src/master/
Author: Jin BENIYAMA
Author-email: beniyama@ioa.s.u-tokyo.ac.jp
Maintainer: Jin BENIYAMA
Maintainer-email: beniyama@ioa.s.u-tokyo.ac.jp
License: UNKNOWN
Platform: UNKNOWN
Requires-Dist: astropy
Requires-Dist: astroquery
